mlx/jira_juggler/__init__.py
mlx/jira_juggler/_version.py
mlx/jira_juggler/jira_juggler.py
mlx_jira_juggler-3.5.0.dist-info/licenses/LICENSE
mlx_jira_juggler-3.5.0.dist-info/METADATA
mlx_jira_juggler-3.5.0.dist-info/WHEEL
mlx_jira_juggler-3.5.0.dist-info/entry_points.txt
mlx_jira_juggler-3.5.0.dist-info/top_level.txt
mlx_jira_juggler-3.5.0.dist-info/RECORD
