Metadata-Version: 2.4
Name: mlx.jira_juggler
Version: 3.5.0
Summary: A Python script for extracting data from Jira, and converting to TaskJuggler (tj3) output
Author-email: Jasper Craeghs <jce@melexis.com>
License-Expression: Apache-2.0
Project-URL: Homepage, https://github.com/melexis/jira-juggler
Project-URL: Repository, https://github.com/melexis/jira-juggler
Keywords: Jira,taskjuggler,gantt,project planning,planning,software engineering
Classifier: Development Status :: 4 - Beta
Classifier: Intended Audience :: Developers
Classifier: Operating System :: Unix
Classifier: Operating System :: POSIX
Classifier: Operating System :: Microsoft :: Windows
Classifier: Programming Language :: Python
Classifier: Programming Language :: Python :: 3.10
Classifier: Programming Language :: Python :: 3.11
Classifier: Programming Language :: Python :: 3.12
Classifier: Programming Language :: Python :: 3.13
Requires-Python: >=3.10
License-File: LICENSE
Requires-Dist: jira>=3.10.5
Requires-Dist: python-dateutil<3.0,>=2.8.0
Requires-Dist: natsort>=8.3.1
Requires-Dist: python-decouple
Dynamic: license-file
